[
 {
  "gt": "",
  "image_path": "data/orcas/prepared/pages/training/feb1585_jul0586_pg079.jpg-22.png",
  "sol": {
   "x0": 539.0,
   "x1": 548.0,
   "y0": 285.0,
   "y1": 285.0
  },
  "steps": [
   {
    "base_point": [
     518.5037618800623,
     294.81320413752366
    ],
    "lower_point": [
     518.5734121688711,
     295.02235406296376
    ],
    "stop_confidence": 0.0,
    "upper_point": [
     508.61239850901717,
     265.1108447225723
    ]
   },
   {
    "base_point": [
     548.2061212950136,
     284.92184076647857
    ],
    "lower_point": [
     548.0,
     285.0
    ],
    "stop_confidence": 0,
    "upper_point": [
     539.0,
     255.0
    ]
   },
   {
    "base_point": [
     578.0,
     275.0
    ],
    "lower_point": [
     578.0,
     275.0
    ],
    "stop_confidence": 0,
    "upper_point": [
     570.0,
     245.0
    ]
   },
   {
    "base_point": [
     609.0,
     270.0
    ],
    "lower_point": [
     609.0,
     270.0
    ],
    "stop_confidence": 0,
    "upper_point": [
     607.8437056712992,
     248.03040775468477
    ]
   },
   {
    "base_point": [
     628.0,
     269.0
    ],
    "lower_point": [
     628.0,
     269.0
    ],
    "stop_confidence": 0,
    "upper_point": [
     626.0,
     246.0
    ]
   },
   {
    "base_point": [
     651.0,
     268.0
    ],
    "lower_point": [
     651.0,
     268.0
    ],
    "stop_confidence": 0,
    "upper_point": [
     651.0,
     246.0
    ]
   },
   {
    "base_point": [
     668.0,
     268.0
    ],
    "lower_point": [
     668.0,
     268.0
    ],
    "stop_confidence": 0,
    "upper_point": [
     668.0,
     246.0
    ]
   },
   {
    "base_point": [
     679.0,
     268.0
    ],
    "lower_point": [
     679.0,
     268.0
    ],
    "stop_confidence": 0,
    "upper_point": [
     679.0,
     246.0
    ]
   },
   {
    "base_point": [
     694.0,
     268.0
    ],
    "lower_point": [
     694.0,
     268.0
    ],
    "stop_confidence": 0,
    "upper_point": [
     694.0,
     246.0
    ]
   },
   {
    "base_point": [
     716.0,
     268.0
    ],
    "lower_point": [
     716.0,
     268.0
    ],
    "stop_confidence": 0,
    "upper_point": [
     716.0,
     242.0
    ]
   },
   {
    "base_point": [
     742.0,
     268.0
    ],
    "lower_point": [
     742.0,
     268.0
    ],
    "stop_confidence": 0,
    "upper_point": [
     743.0,
     238.0
    ]
   },
   {
    "base_point": [
     772.0,
     270.0
    ],
    "lower_point": [
     771.0,
     290.0
    ],
    "stop_confidence": 0,
    "upper_point": [
     773.0,
     243.0
    ]
   },
   {
    "base_point": [
     799.0,
     271.0
    ],
    "lower_point": [
     798.0,
     286.0
    ],
    "stop_confidence": 0,
    "upper_point": [
     801.0,
     242.0
    ]
   },
   {
    "base_point": [
     826.5683762631352,
     272.9699987941631
    ],
    "lower_point": [
     825.0,
     295.0
    ],
    "stop_confidence": 0,
    "upper_point": [
     828.0,
     244.0
    ]
   },
   {
    "base_point": [
     857.0625029096576,
     273.609035816798
    ],
    "lower_point": [
     856.6660714391229,
     292.5262988875799
    ],
    "stop_confidence": 0.38218157226562494,
    "upper_point": [
     857.6106351447758,
     247.45278319810615
    ]
   },
   {
    "base_point": [
     883.2187555283494,
     274.1571680519162
    ],
    "lower_point": [
     882.8619672048682,
     291.1827048156199
    ],
    "stop_confidence": 0.46325039062499995,
    "upper_point": [
     883.7120745399558,
     250.61654069509353
    ]
   },
   {
    "base_point": [
     906.759382885172,
     274.6504870635226
    ],
    "lower_point": [
     906.4382733940389,
     289.9734701508559
    ],
    "stop_confidence": 0.561515625,
    "upper_point": [
     907.2203152038802,
     252.65531619813555
    ]
   },
   {
    "base_point": [
     927.9459475063125,
     275.0944741739683
    ],
    "lower_point": [
     927.6569489642926,
     288.8851589525683
    ],
    "stop_confidence": 0.6806249999999999,
    "upper_point": [
     928.4068798250207,
     253.09930330858128
    ]
   },
   {
    "base_point": [
     947.0138556653388,
     275.4940625733695
    ],
    "lower_point": [
     946.753756977521,
     287.90567887410947
    ],
    "stop_confidence": 0.825,
    "upper_point": [
     947.474787984047,
     253.49889170798247
    ]
   },
   {
    "base_point": [
     964.1749730084626,
     275.85369213283053
    ],
    "lower_point": [
     963.9408841894266,
     287.02414680349654
    ],
    "stop_confidence": 1,
    "upper_point": [
     964.4986396119776,
     260.4086865240192
    ]
   }
  ]
 }
]