[
 {
  "gt": "",
  "image_path": "data/orcas/prepared/pages/training/jul0183_nov2284_pg052.jpg-7.png",
  "sol": {
   "x0": 346.0,
   "x1": 350.0,
   "y0": 351.0,
   "y1": 351.0
  },
  "steps": [
   {
    "base_point": [
     323.89993182894557,
     350.80247194520683
    ],
    "lower_point": [
     323.89931853104986,
     350.96423561067485
    ],
    "stop_confidence": 0.0,
    "upper_point": [
     323.99937324674744,
     324.5737691316812
    ]
   },
   {
    "base_point": [
     350.1286346424712,
     350.9019133630087
    ],
    "lower_point": [
     350.0,
     351.0
    ],
    "stop_confidence": 0,
    "upper_point": [
     346.0,
     325.0
    ]
   },
   {
    "base_point": [
     376.0,
     351.0
    ],
    "lower_point": [
     376.0,
     353.0
    ],
    "stop_confidence": 0,
    "upper_point": [
     379.0,
     326.0
    ]
   },
   {
    "base_point": [
     401.0,
     355.0
    ],
    "lower_point": [
     401.0,
     355.0
    ],
    "stop_confidence": 0,
    "upper_point": [
     403.0,
     323.0
    ]
   },
   {
    "base_point": [
     433.0,
     354.0
    ],
    "lower_point": [
     433.0,
     357.0
    ],
    "stop_confidence": 0,
    "upper_point": [
     433.0,
     332.0
    ]
   },
   {
    "base_point": [
     455.0,
     354.0
    ],
    "lower_point": [
     455.0,
     354.0
    ],
    "stop_confidence": 0,
    "upper_point": [
     455.0,
     332.0
    ]
   },
   {
    "base_point": [
     476.9996395579064,
     354.12593380086327
    ],
    "lower_point": [
     476.9996395579064,
     354.12593380086327
    ],
    "stop_confidence": 0.38218157226562494,
    "upper_point": [
     477.12557335876966,
     332.1262942429569
    ]
   },
   {
    "base_point": [
     496.79931516002216,
     354.2392742216402
    ],
    "lower_point": [
     496.79931516002216,
     354.2392742216402
    ],
    "stop_confidence": 0.46325039062499995,
    "upper_point": [
     496.9252489608854,
     332.2396346637338
    ]
   },
   {
    "base_point": [
     514.6190232019264,
     354.3412806003394
    ],
    "lower_point": [
     514.6190232019264,
     354.3412806003394
    ],
    "stop_confidence": 0.561515625,
    "upper_point": [
     514.7449570027896,
     332.341641042433
    ]
   },
   {
    "base_point": [
     530.6567604396403,
     354.43308634116875
    ],
    "lower_point": [
     530.6567604396403,
     354.43308634116875
    ],
    "stop_confidence": 0.6806249999999999,
    "upper_point": [
     530.7826942405036,
     332.43344678326235
    ]
   },
   {
    "base_point": [
     545.0907239535827,
     354.5157115079151
    ],
    "lower_point": [
     545.0907239535827,
     354.5157115079151
    ],
    "stop_confidence": 0.825,
    "upper_point": [
     545.2166577544459,
     332.5160719500087
    ]
   },
   {
    "base_point": [
     558.0812911161308,
     354.59007415798686
    ],
    "lower_point": [
     558.0812911161308,
     354.59007415798686
    ],
    "stop_confidence": 1,
    "upper_point": [
     558.1482175011954,
     342.89856371169355
    ]
   }
  ]
 }
]