[
 {
  "gt": "",
  "image_path": "data/orcas/prepared/pages/training/sep2586_sep0387_pg052.jpg-8.png",
  "sol": {
   "x0": 91.0,
   "x1": 88.0,
   "y0": 329.0,
   "y1": 329.0
  },
  "steps": [
   {
    "base_point": [
     60.210144971413115,
     325.91948348598896
    ],
    "lower_point": [
     60.13901741816507,
     326.47992224443186
    ],
    "stop_confidence": 0.0,
    "upper_point": [
     63.685829865937755,
     298.5333519789342
    ]
   },
   {
    "base_point": [
     87.59627647846787,
     329.3951683805136
    ],
    "lower_point": [
     88.0,
     329.0
    ],
    "stop_confidence": 0,
    "upper_point": [
     91.0,
     302.0
    ]
   },
   {
    "base_point": [
     116.0,
     333.0
    ],
    "lower_point": [
     116.0,
     333.0
    ],
    "stop_confidence": 0,
    "upper_point": [
     116.0,
     309.0
    ]
   },
   {
    "base_point": [
     140.0,
     330.0
    ],
    "lower_point": [
     140.0,
     330.0
    ],
    "stop_confidence": 0,
    "upper_point": [
     139.0,
     307.0
    ]
   },
   {
    "base_point": [
     163.0,
     330.0
    ],
    "lower_point": [
     163.0,
     330.0
    ],
    "stop_confidence": 0,
    "upper_point": [
     163.0,
     308.0
    ]
   },
   {
    "base_point": [
     174.1682696503717,
     329.74566227999503
    ],
    "lower_point": [
     174.0,
     330.0
    ],
    "stop_confidence": 0,
    "upper_point": [
     170.6678745349037,
     308.0259193248952
    ]
   },
   {
    "base_point": [
     203.78392241143644,
     324.97274731131733
    ],
    "lower_point": [
     203.78392241143644,
     324.97274731131733
    ],
    "stop_confidence": 0.38218157226562494,
    "upper_point": [
     200.2835272959684,
     303.2530043562175
    ]
   },
   {
    "base_point": [
     220.6894525817292,
     322.2482198915029
    ],
    "lower_point": [
     220.6894525817292,
     322.2482198915029
    ],
    "stop_confidence": 0.46325039062499995,
    "upper_point": [
     217.1890574662612,
     300.5284769364031
    ]
   },
   {
    "base_point": [
     235.90442973499268,
     319.79614521366994
    ],
    "lower_point": [
     235.90442973499268,
     319.79614521366994
    ],
    "stop_confidence": 0.561515625,
    "upper_point": [
     232.40403461952465,
     298.07640225857017
    ]
   },
   {
    "base_point": [
     249.5979091729298,
     317.5892780036203
    ],
    "lower_point": [
     249.5979091729298,
     317.5892780036203
    ],
    "stop_confidence": 0.6806249999999999,
    "upper_point": [
     246.09751405746178,
     295.86953504852045
    ]
   },
   {
    "base_point": [
     261.9220406670732,
     315.6030975145756
    ],
    "lower_point": [
     261.9220406670732,
     315.6030975145756
    ],
    "stop_confidence": 0.825,
    "upper_point": [
     258.42164555160514,
     293.88335455947583
    ]
   },
   {
    "base_point": [
     273.0137590118022,
     313.8155350744354
    ],
    "lower_point": [
     273.0137590118022,
     313.8155350744354
    ],
    "stop_confidence": 1,
    "upper_point": [
     271.40495281567604,
     303.83298856417923
    ]
   }
  ]
 }
]